{
 "slug": "nixa",
 "taxonomy": "locations",
 "route": "/locations/nixa",
 "title": "Commercial Roofing in Nixa, MO | Commercial Roofers of Springfield",
 "metaDescription": "Commercial roof scoping for Nixa, MO along the fast-growing US-160 retail corridor and its expanding base of CoxHealth and Mercy clinic buildings.",
 "internalLinks": [
  {
   "anchor": "Willard Is Growing Faster Than Its Roof Inventory",
   "slug": "willard",
   "taxonomy": "locations",
   "href": "/locations/willard"
  },
  {
   "anchor": "Commercial Roofing Near Ash Grove's Historic Lime Kilns",
   "slug": "ash-grove",
   "taxonomy": "locations",
   "href": "/locations/ash-grove"
  },
  {
   "anchor": "Commercial Roof Work in Aurora's Manufacturing and Grain Corridor",
   "slug": "aurora",
   "taxonomy": "locations",
   "href": "/locations/aurora"
  },
  {
   "anchor": "Commercial Roofing for a Fast-Growing Corner of Greene County",
   "slug": "battlefield",
   "taxonomy": "locations",
   "href": "/locations/battlefield"
  },
  {
   "anchor": "Ag and Highway 60 Roofing Work in Billings",
   "slug": "billings",
   "taxonomy": "locations",
   "href": "/locations/billings"
  },
  {
   "anchor": "PVC Roofing for the Roofs Regular Membrane Can't Handle",
   "slug": "pvc-roofing",
   "taxonomy": "services",
   "href": "/services/pvc-roofing"
  },
  {
   "anchor": "A Strip Center Roof Is Really Several Roofs Wearing One Membrane",
   "slug": "multi-tenant-retail-strip-roofing",
   "taxonomy": "project-types",
   "href": "/project-types/multi-tenant-retail-strip-roofing"
  },
  {
   "anchor": "Storm Restoration Roofing Documented for the Insurance Claim Process",
   "slug": "insurance-restoration",
   "taxonomy": "industries",
   "href": "/industries/insurance-restoration"
  }
 ],
 "html": "<h1>Nixa's Growth Is Outrunning Its Roof Bids</h1>\n<p>Nixa has added retail and medical space along US-160 faster than most contractors in the area have adjusted how they scope it. New construction doesn't mean a simpler bid. It usually means more moving pieces, more phasing questions, and more places for an underbid quote to leave something out.</p>\n<h2>US-160's Retail Corridor Keeps Adding Roof</h2>\n<p>The stretch of US-160 through Nixa has filled in with retail pads and multi-tenant centers over a short enough window that some of these roofs are still under original manufacturer warranty. That matters for how we scope repair work, because warranty terms often restrict who can touch the roof and how, and a contractor who doesn't check that first can put the whole warranty at risk with one unauthorized patch.</p>\n<p>We pull warranty documentation before we recommend any repair path on a newer 160-corridor roof. It changes what's allowed, what voids coverage, and who has to sign off on the work.</p>\n<p>We also see multi-tenant centers along 160 where the original developer roof and a later outparcel addition sit right next to each other under different warranty terms entirely. A repair crew that doesn't check which section they're standing on can accidentally trigger a warranty dispute between the developer and the outparcel owner over who was responsible for the damage.</p>\n<h2>Clinic Roofs Need a Different Kind of Scope</h2>\n<p>Nixa's medical clinic buildings, tied to the CoxHealth and Mercy networks serving the growing population south of Springfield, bring scheduling constraints most retail roofs don't. Patient traffic, exam rooms directly under the roof deck, and equipment sensitive to vibration or dust change how we plan a project, not only when we start it.</p>\n<p>We sequence noisy work, deck penetration, and material staging around clinic hours when asked, and we document dust and debris control the same way we'd document any other part of the scope. A bid that doesn't mention how it handles an occupied medical building probably hasn't thought about it.</p>\n<h2>What Belongs in a Nixa Bid</h2>\n<p>Given how fast this corridor is building out, we make sure every scope answers:</p>\n<ul>\n<li>Is the existing roof still under manufacturer warranty, and does the scope respect it</li>\n<li>What is the phasing plan for occupied medical or retail space</li>\n<li>Are all rooftop penetrations mapped, including recent tenant additions</li>\n<li>What is the drainage plan for the specific roof section, not the building as a whole</li>\n<li>Is there a documented dust and debris control plan for sensitive interiors</li>\n<li>What warranty terms apply to the new work once it's complete</li>\n</ul>\n<p>Skip any one of those and the bid is incomplete for a building growing this fast.</p>\n<h2>Storms Don't Wait for the Building to Finish Growing</h2>\n<p>Southwest Missouri's hail and severe wind season hits Nixa the same as anywhere else in the metro, and a roof that's only a few years old isn't exempt. We treat storm inspection on newer construction the same way we treat it on older buildings: documented, photographed, and separated cleanly from any pre-existing condition so the record holds up if it's needed later.</p>\n<h2>New Construction Doesn't Mean the Old Rules Don't Apply</h2>\n<p>Some owners assume a roof under five years old doesn't need the same scrutiny as an older one. We disagree. New roofs still get penetrations added during tenant buildout, still take hail hits, and still have installation errors that don't show up until the first hard rain. We inspect new roofs with the same checklist we use on a fifteen-year-old one, just with a different repair path in mind.</p>\n<p>An owner who assumes a young roof is a low-priority item on the maintenance list is usually the one surprised by a leak during the first major storm. We recommend the same inspection interval for a three-year-old membrane as for an older one, since the cost of catching a problem early doesn't change with the roof's age.</p>\n<p>Retail buildout also keeps moving on this corridor even after a center opens, with new tenants replacing old ones and each turnover bringing its own rooftop equipment changes. A roof that was clean at handoff two years ago can have three or four new penetrations by the time the next tenant moves in, and none of those are guaranteed to appear on the property's original roof plan. Property managers who ask us to re-survey a center every couple of tenant turnovers catch these gaps far earlier than owners who wait for a leak.</p>\n<h2>Roofing Questions Nixa Owners Ask Us</h2>\n<h3>Will a repair void the manufacturer warranty on a newer roof?</h3>\n<p>It can, depending on who performs the work and how. We check warranty terms first and scope the repair to stay within them wherever possible.</p>\n<h3>Can you schedule work around an operating medical clinic?</h3>\n<p>Yes. We sequence loud or disruptive work outside patient hours when needed and document dust and debris control for sensitive interior spaces.</p>\n<h3>Do new roofs really need storm inspections?</h3>\n<p>Yes. Hail and wind don't check the install date. We inspect new roofs with the same process we use on older ones and document findings the same way.</p>\n<h3>What's the most common gap you find on a Nixa bid from another contractor?</h3>\n<p>Missing warranty review. A repair that ignores the manufacturer's terms can cost an owner coverage on a roof that still has a decade of warranty life left.</p>\n<h3>How do you handle a roof with penetrations added after the original install?</h3>\n<p>We walk the roof and map every penetration ourselves rather than relying on the original construction drawings, since tenant buildouts rarely update them.</p>",
 "image": "/images/locations/commercial-roofers-nixa-mo.webp"
}
